Metadata-Version: 2.1
Name: last-task
Version: 0.2
Summary: last_task
Home-page: UNKNOWN
Author: Moontrey
Author-email: golubev.ruslan2013@yandex.ru
License: UNKNOWN
Platform: UNKNOWN
